lsd/__init__.py
lsd/constants.py
lsd/error.py
lsd/helpers.py
lsd-0.4.0.dist-info/LICENSE
lsd-0.4.0.dist-info/METADATA
lsd-0.4.0.dist-info/WHEEL
lsd-0.4.0.dist-info/RECORD
